odoo/addons/purchase_order_owner/README.rst
odoo/addons/purchase_order_owner/__init__.py
odoo/addons/purchase_order_owner/__manifest__.py
odoo/addons/purchase_order_owner/i18n/es.po
odoo/addons/purchase_order_owner/i18n/it.po
odoo/addons/purchase_order_owner/i18n/purchase_order_owner.pot
odoo/addons/purchase_order_owner/models/__init__.py
odoo/addons/purchase_order_owner/models/purchase_order.py
odoo/addons/purchase_order_owner/readme/CONTRIBUTORS.md
odoo/addons/purchase_order_owner/readme/DESCRIPTION.md
odoo/addons/purchase_order_owner/static/description/icon.png
odoo/addons/purchase_order_owner/static/description/index.html
odoo/addons/purchase_order_owner/tests/__init__.py
odoo/addons/purchase_order_owner/tests/test_purchase_order_owner.py
odoo/addons/purchase_order_owner/views/purchase_order_views.xml
odoo_addon_purchase_order_owner-19.0.1.0.0.2.dist-info/METADATA
odoo_addon_purchase_order_owner-19.0.1.0.0.2.dist-info/WHEEL
odoo_addon_purchase_order_owner-19.0.1.0.0.2.dist-info/top_level.txt
odoo_addon_purchase_order_owner-19.0.1.0.0.2.dist-info/RECORD
