Metadata-Version: 2.1
Name: odoo-addon-purchase_order_owner
Version: 19.0.1.0.0.2
Requires-Dist: odoo==19.0.*
Summary: Purchase Order Owner
Home-page: https://github.com/OCA/purchase-workflow
License: LGPL-3
Author: Quartile Limited, Odoo Community Association (OCA)
Author-email: support@odoo-community.org
Classifier: Programming Language :: Python
Classifier: Framework :: Odoo
Classifier: Framework :: Odoo :: 19.0
Classifier: License :: OSI Approved :: GNU Lesser General Public License v3 (LGPLv3)
